rio_vrt/__init__.py
rio_vrt/enums.py
rio_vrt/vrt.py
rio_vrt-0.3.1.dist-info/METADATA
rio_vrt-0.3.1.dist-info/WHEEL
rio_vrt-0.3.1.dist-info/top_level.txt
rio_vrt-0.3.1.dist-info/RECORD
