Metadata-Version: 2.1
Name: rio-vrt
Version: 0.3.1
Summary: A simple librairy to build a vrt from multiple raster source relying only on rasterio
Author-email: pierrick rambaud <pierrick.rambaud49@gmail.com>
License: MIT
Project-URL: Homepage, https://github.com/12rambau/rio-vrt
Keywords: skeleton,Python
Classifier: Development Status :: 3 - Alpha
Classifier: Intended Audience :: Developers
Classifier: License :: OSI Approved :: MIT License
Classifier: Programming Language :: Python :: 3.7
Classifier: Programming Language :: Python :: 3.8
Classifier: Programming Language :: Python :: 3.9
Classifier: Programming Language :: Python :: 3.10
Requires-Python: >=3.6.9
Requires-Dist: rasterio
Provides-Extra: dev
Requires-Dist: pre-commit; extra == "dev"
Requires-Dist: commitizen; extra == "dev"
Requires-Dist: nox; extra == "dev"
Requires-Dist: mypy; extra == "dev"
Provides-Extra: doc
Requires-Dist: sphinx; extra == "doc"
Requires-Dist: pydata-sphinx-theme; extra == "doc"
Requires-Dist: sphinx-copybutton; extra == "doc"
Requires-Dist: sphinx-design; extra == "doc"
Requires-Dist: sphinx-icon; extra == "doc"
Requires-Dist: sphinx-btn; extra == "doc"
Provides-Extra: test
Requires-Dist: pytest; extra == "test"
Requires-Dist: pytest-sugar; extra == "test"
Requires-Dist: pytest-cov; extra == "test"
Requires-Dist: pytest-deadfixtures; extra == "test"
Requires-Dist: pytest-regressions; extra == "test"
Requires-Dist: xmlschema; extra == "test"
Requires-Dist: natsort; extra == "test"
Requires-Dist: beautifulsoup4; extra == "test"
Requires-Dist: lxml; extra == "test"
